{
    "Hodnota": "Hodnota",
    "Hodnota:hodnoty": {
        "34": "34",
        "47.8": "47.8",
        "17": "17",
        "26.2": "26.2",
        "6.1": "6.1",
        "44.3": "44.3",
        "50.9": "50.9",
        "8.6": "8.6",
        "26.9": "26.9",
        "30.1": "30.1",
        "10.6": "10.6",
        "7.5": "7.5",
        "16": "16",
        "30.3": "30.3",
        "12.3": "12.3",
        "14.5": "14.5",
        "34.3": "34.3",
        "15": "15",
        "16.4": "16.4",
        "44.7": "44.7",
        "44.8": "44.8",
        "56.4": "56.4",
        "45.2": "45.2",
        "57.6": "57.6",
        "40.2": "40.2",
        "32.7": "32.7",
        "35.7": "35.7",
        "53.3": "53.3",
        "46.8": "46.8",
        "0": "0",
        "2.4": "2.4",
        "3.3": "3.3",
        "1.8": "1.8",
        "21.4": "21.4",
        "4.8": "4.8",
        "6.7": "6.7"
    },
    "Jednotka": "Jednotka",
    "Jednotka:hodnoty": {
        "%": "%"
    },
    "Obdobi": "Obdobi",
    "Obdobi:hodnoty": {
        "2007–2012": "2007–2012"
    },
    "Stanoviště": "Stanoviště",
    "Stanoviště:hodnoty": {
        "Coastal": "Coastal",
        "Dunes": "Dunes",
        "Freshwater": "Freshwater",
        "Heath & scrub": "Heath & scrub",
        "Sclerophyllous scrubs": "Sclerophyllous scrubs",
        "Grasslands": "Grasslands",
        "Bogs, mires & fens": "Bogs, mires & fens",
        "Rocky": "Rocky",
        "Forests": "Forests",
        "EU-27": "EU-27"
    },
    "Stav": "Stav",
    "Stav:hodnoty": {
        "Nepříznivý stav": "Nepříznivý stav",
        "Příznivý stav": "Příznivý stav",
        "Nedostatečný stav": "Nedostatečný stav",
        "Neznámý stav": "Neznámý stav"
    }
}